cloudmesh_windows-4.1.3-py3.8-nspkg.pth
cloudmesh/test/CloudmeshTest.py
cloudmesh/test/__init__.py
cloudmesh/test/__version__.py
cloudmesh/test/command/__init__.py
cloudmesh/test/command/test.py
cloudmesh_windows-4.1.3.dist-info/LICENSE
cloudmesh_windows-4.1.3.dist-info/METADATA
cloudmesh_windows-4.1.3.dist-info/WHEEL
cloudmesh_windows-4.1.3.dist-info/namespace_packages.txt
cloudmesh_windows-4.1.3.dist-info/top_level.txt
cloudmesh_windows-4.1.3.dist-info/RECORD
