Metadata-Version: 2.1
Name: cloudmesh-windows
Version: 4.1.3
Summary: A command called windows and foo for the cloudmesh shell
Home-page: https://github.com/cloudmesh/cloudmesh-windows
Author: Gregor von Laszewski
Author-email: laszewski@gmail.com
License: Apache 2.0
Platform: UNKNOWN
Classifier: Development Status :: 5 - Production/Stable
Classifier: Environment :: Web Environment
Classifier: Intended Audience :: Developers
Classifier: License :: OSI Approved :: BSD License
Classifier: Operating System :: OS Independent
Classifier: Programming Language :: Python
Classifier: Programming Language :: Python :: 2
Classifier: Programming Language :: Python :: 3
Requires-Dist: psutil
Requires-Dist: yamllint
